{"assets":[{"id":"comp_0","layers":[{"ddd":0,"ind":0,"ty":4,"nm":"\rlines","ks":{"o":{"k":100},"r":{"k":0},"p":{"k":[376,377.1,0]},"a":{"k":[325.5,331,0]},"s":{"k":[100,100,100]}},"shapes":[{"ty":"gr","it":[{"ind":0,"ty":"sh","closed":true,"ks":{"k":{"i":[[0,0],[0,0],[0,0],[0,0]],"o":[[0,0],[0,0],[0,0],[0,0]],"v":[[52.288,324.8],[-128.946,220.164],[136.816,65.449],[317.577,169.811]]}},"nm":"Path 1"},{"ind":1,"ty":"sh","closed":true,"ks":{"k":{"i":[[0,0],[0,0],[0,0],[0,0],[0,0]],"o":[[0,0],[0,0],[0,0],[0,0],[0,0]],"v":[[-47.436,-40.917],[-47.426,-40.922],[131.827,62.569],[-133.935,217.284],[-315.026,112.732]]}},"nm":"Path 2"},{"ind":2,"ty":"sh","closed":true,"ks":{"k":{"i":[[0,0],[0,0],[0,0],[0,0]],"o":[[0,0],[0,0],[0,0],[0,0]],"v":[[133.486,-218.916],[134.438,58.303],[-44.926,-45.253],[-44.926,-321.923]]}},"nm":"Path 3"},{"ind":3,"ty":"sh","closed":true,"ks":{"k":{"i":[[0,0],[0,0],[0,0],[0,0]],"o":[[0,0],[0,0],[0,0],[0,0]],"v":[[320.046,165.464],[139.447,61.195],[138.495,-216.025],[320.046,-111.206]]}},"nm":"Path 4"},{"ind":4,"ty":"sh","closed":true,"ks":{"k":{"i":[[0,0],[0,0],[0,0],[0,0],[0,0],[0,0]],"o":[[0,0],[0,0],[0,0],[0,0],[0,0],[0,0]],"v":[[-49.926,-330.413],[-49.926,-45.082],[-325.047,112.549],[52.303,330.412],[325.047,171.407],[325.047,-113.921]]}},"nm":"Path 5"},{"ty":"mm","mm":1,"nm":"Merge Paths 1"},{"ty":"fl","fillEnabled":true,"c":{"k":[0.95,0.93,0.91,1]},"o":{"k":100},"nm":"Fill 1"},{"ty":"tr","p":{"k":[325.296,330.663],"ix":2},"a":{"k":[0,0],"ix":1},"s":{"k":[100,100],"ix":3},"r":{"k":0,"ix":6},"o":{"k":100,"ix":7},"sk":{"k":0,"ix":4},"sa":{"k":0,"ix":5},"nm":"Transform"}],"nm":"Group 1"}],"ip":0,"op":450,"st":0,"bm":0,"sr":1},{"ddd":0,"ind":1,"ty":4,"nm":"\rback top","ks":{"o":{"k":100},"r":{"k":0},"p":{"k":[521.301,150.098,0]},"a":{"k":[196.682,113.342,0]},"s":{"k":[100,100,100]}},"shapes":[{"ty":"gr","it":[{"ind":0,"ty":"sh","closed":true,"ks":{"k":{"i":[[0,0],[0,0],[0,0],[0,0]],"o":[[0,0],[0,0],[0,0],[0,0]],"v":[[-196.432,-103.398],[-179.725,-113.092],[196.431,102.814],[178.54,113.092]]}},"nm":"Path 1"},{"ty":"fl","fillEnabled":true,"c":{"k":[0.97,0.75,0.75,1]},"o":{"k":100},"nm":"Fill 1"},{"ty":"tr","p":{"k":[196.681,113.343],"ix":2},"a":{"k":[0,0],"ix":1},"s":{"k":[100,100],"ix":3},"r":{"k":0,"ix":6},"o":{"k":100,"ix":7},"sk":{"k":0,"ix":4},"sa":{"k":0,"ix":5},"nm":"Transform"}],"nm":"Group 1"}],"ip":0,"op":450,"st":0,"bm":0,"sr":1},{"ddd":0,"ind":2,"ty":4,"nm":"\rback side","ks":{"o":{"k":100},"r":{"k":0},"p":{"k":[708.786,406.344,0]},"a":{"k":[9.196,153.682,0]},"s":{"k":[100,100,100]}},"shapes":[{"ty":"gr","it":[{"ind":0,"ty":"sh","closed":true,"ks":{"k":{"i":[[0,0],[0,0],[0,0],[0,0]],"o":[[0,0],[0,0],[0,0],[0,0]],"v":[[8.946,-153.432],[8.946,153.432],[-8.946,142.177],[-8.946,-143.152]]}},"nm":"Path 1"},{"ty":"fl","fillEnabled":true,"c":{"k":[0.98,0.7,0.7,1]},"o":{"k":100},"nm":"Fill 1"},{"ty":"tr","p":{"k":[9.195,153.682],"ix":2},"a":{"k":[0,0],"ix":1},"s":{"k":[100,100],"ix":3},"r":{"k":0,"ix":6},"o":{"k":100,"ix":7},"sk":{"k":0,"ix":4},"sa":{"k":0,"ix":5},"nm":"Transform"}],"nm":"Group 1"}],"ip":0,"op":450,"st":0,"bm":0,"sr":1},{"ddd":0,"ind":3,"ty":4,"nm":"\rback front","ks":{"o":{"k":100},"r":{"k":0},"p":{"k":[512.355,297.61,0]},"a":{"k":[187.736,251.16,0]},"s":{"k":[100,100,100]}},"shapes":[{"ty":"gr","it":[{"ind":0,"ty":"sh","closed":true,"ks":{"k":{"i":[[0,0],[0,0],[0,0],[0,0]],"o":[[0,0],[0,0],[0,0],[0,0]],"v":[[-187.486,-250.91],[187.486,-34.42],[187.486,250.91],[-187.486,34.42]]}},"nm":"Path 1"},{"ty":"fl","fillEnabled":true,"c":{"k":[0.98,0.64,0.64,1]},"o":{"k":100},"nm":"Fill 1"},{"ty":"tr","p":{"k":[187.736,251.16],"ix":2},"a":{"k":[0,0],"ix":1},"s":{"k":[100,100],"ix":3},"r":{"k":0,"ix":6},"o":{"k":100,"ix":7},"sk":{"k":0,"ix":4},"sa":{"k":0,"ix":5},"nm":"Transform"}],"nm":"Group 1"}],"ip":0,"op":450,"st":0,"bm":0,"sr":1},{"ddd":0,"ind":4,"ty":4,"nm":"\rfront side","ks":{"o":{"k":100},"r":{"k":0},"p":{"k":[572.414,638.312,0]},"a":{"k":[145.568,90.042,0]},"s":{"k":[100,100,100]}},"shapes":[{"ty":"gr","it":[{"ind":0,"ty":"sh","closed":true,"ks":{"k":{"i":[[0,0],[0,0],[0,0],[0,0]],"o":[[0,0],[0,0],[0,0],[0,0]],"v":[[145.317,-78.538],[-145.318,89.792],[-145.318,69.246],[127.426,-89.792]]}},"nm":"Path 1"},{"ty":"fl","fillEnabled":true,"c":{"k":[0.98,0.64,0.64,1]},"o":{"k":100},"nm":"Fill 1"},{"ty":"tr","p":{"k":[145.568,90.042],"ix":2},"a":{"k":[0,0],"ix":1},"s":{"k":[100,100],"ix":3},"r":{"k":0,"ix":6},"o":{"k":100,"ix":7},"sk":{"k":0,"ix":4},"sa":{"k":0,"ix":5},"nm":"Transform"}],"nm":"Group 1"}],"ip":0,"op":450,"st":0,"bm":0,"sr":1},{"ddd":0,"ind":5,"ty":4,"nm":"\rfront front","ks":{"o":{"k":100},"r":{"k":0},"p":{"k":[238.422,608.883,0]},"a":{"k":[188.924,119.472,0]},"s":{"k":[100,100,100]}},"shapes":[{"ty":"gr","it":[{"ind":0,"ty":"sh","closed":true,"ks":{"k":{"i":[[0,0],[0,0],[0,0],[0,0]],"o":[[0,0],[0,0],[0,0],[0,0]],"v":[[-188.674,-98.534],[188.674,119.221],[188.674,98.641],[-188.674,-119.221]]}},"nm":"Path 1"},{"ty":"fl","fillEnabled":true,"c":{"k":[0.98,0.65,0.65,1]},"o":{"k":100},"nm":"Fill 1"},{"ty":"tr","p":{"k":[188.924,119.472],"ix":2},"a":{"k":[0,0],"ix":1},"s":{"k":[100,100],"ix":3},"r":{"k":0,"ix":6},"o":{"k":100,"ix":7},"sk":{"k":0,"ix":4},"sa":{"k":0,"ix":5},"nm":"Transform"}],"nm":"Group 1"}],"ip":0,"op":450,"st":0,"bm":0,"sr":1},{"ddd":0,"ind":6,"ty":4,"nm":"\rfront top","ks":{"o":{"k":100},"r":{"k":0},"p":{"k":[374.794,519.778,0]},"a":{"k":[325.297,187.997,0]},"s":{"k":[100,100,100]}},"shapes":[{"ty":"gr","it":[{"ind":0,"ty":"sh","closed":true,"ks":{"k":{"i":[[0,0],[0,0],[0,0],[0,0]],"o":[[0,0],[0,0],[0,0],[0,0]],"v":[[-325.047,-30.116],[52.302,187.747],[325.047,28.742],[-49.925,-187.747]]}},"nm":"Path 1"},{"ty":"fl","fillEnabled":true,"c":{"k":[0.99,0.69,0.69,1]},"o":{"k":100},"nm":"Fill 1"},{"ty":"tr","p":{"k":[325.297,187.997],"ix":2},"a":{"k":[0,0],"ix":1},"s":{"k":[100,100],"ix":3},"r":{"k":0,"ix":6},"o":{"k":100,"ix":7},"sk":{"k":0,"ix":4},"sa":{"k":0,"ix":5},"nm":"Transform"}],"nm":"Group 1"}],"ip":0,"op":450,"st":0,"bm":0,"sr":1}]}],"layers":[{"ddd":0,"ind":0,"ty":4,"nm":"\rracket","ks":{"o":{"k":100},"r":{"k":0},"p":{"k":[{"i":{"x":0.3,"y":1},"o":{"x":0.167,"y":0},"n":"0p3_1_0p167_0","t":0,"s":[357.346,662.771,0],"e":[273.846,628.271,0],"to":[30,18.3333339691162,0],"ti":[30,18.3333339691162,0]},{"i":{"x":0.3,"y":1},"o":{"x":0.7,"y":0},"n":"0p3_1_0p7_0","t":18.25,"s":[273.846,628.271,0],"e":[136.346,542.771,0],"to":[-30,-18.3333339691162,0],"ti":[0,0,0]},{"i":{"x":0.3,"y":1},"o":{"x":0.7,"y":0},"n":"0p3_1_0p7_0","t":36.5,"s":[136.346,542.771,0],"e":[198.611,575.328,0],"to":[0,0,0],"ti":[0,0,0]},{"i":{"x":0.3,"y":1},"o":{"x":0.7,"y":0},"n":"0p3_1_0p7_0","t":54.75,"s":[198.611,575.328,0],"e":[357.346,662.771,0],"to":[0,0,0],"ti":[-18.3451995849609,-11.210955619812,0]},{"t":71}]},"a":{"k":[34.545,60.245,0]},"s":{"k":[100,100,100]}},"shapes":[{"ty":"gr","it":[{"ind":0,"ty":"sh","closed":true,"ks":{"k":{"i":[[0,0],[6.605,27.198],[-9.721,-0.528],[-8.976,-26.081],[0,0]],"o":[[0,0],[-6.605,-27.198],[9.722,0.527],[8.061,22.768],[0,0]],"v":[[-6.329,35.135],[-24.87,0.051],[-8.86,-34.608],[23.415,-1.448],[27.115,28.614]]}},"nm":"Path 1"},{"ty":"fl","fillEnabled":true,"c":{"k":[0.87,0,0,1]},"o":{"k":100},"nm":"Fill 1"},{"ty":"tr","p":{"k":[31.726,39.056],"ix":2},"a":{"k":[0,0],"ix":1},"s":{"k":[100,100],"ix":3},"r":{"k":0,"ix":6},"o":{"k":100,"ix":7},"sk":{"k":0,"ix":4},"sa":{"k":0,"ix":5},"nm":"Transform"}],"nm":"Group 1"},{"ty":"gr","it":[{"ind":0,"ty":"sh","closed":true,"ks":{"k":{"i":[[8.062,22.768],[9.722,0.527],[3.339,-2.747],[0,0],[0,0],[0,0],[-3.276,-13.49],[0,0],[0,0],[0,0],[0,0]],"o":[[-8.975,-26.081],[-3.637,-0.198],[0,0],[0,0],[0,0],[-3.551,5.343],[6.605,27.198],[0,0],[0,0],[0,0],[0,0]],"v":[[21.75,-1.613],[-10.525,-34.773],[-21.583,-31.227],[-21.583,-31.227],[-26.178,-27.543],[-24.736,-27.707],[-26.536,-0.114],[-7.995,34.971],[17.611,29.978],[20.45,32.45],[25.45,28.449]]}},"nm":"Path 1"},{"ty":"fl","fillEnabled":true,"c":{"k":[0.68,0.02,0.04,1]},"o":{"k":100},"nm":"Fill 1"},{"ty":"tr","p":{"k":[38.391,35.221],"ix":2},"a":{"k":[0,0],"ix":1},"s":{"k":[100,100],"ix":3},"r":{"k":0,"ix":6},"o":{"k":100,"ix":7},"sk":{"k":0,"ix":4},"sa":{"k":0,"ix":5},"nm":"Transform"}],"nm":"Group 2"},{"ty":"gr","it":[{"ind":0,"ty":"sh","closed":true,"ks":{"k":{"i":[[0.61,1.468],[0,0],[0.651,6.277],[0.002,0.015],[-1.539,3.165],[-0.615,1.041],[-0.243,0.474],[0,0],[-4.446,-1.093],[-2.674,-8.164],[0,0],[-2.437,0.24],[-0.96,0.386]],"o":[[-0.61,-1.468],[0,0],[-0.002,-0.016],[-0.872,-6.566],[0.768,-1.58],[0.224,-0.424],[0,0],[0,0],[5.511,1.355],[2.675,8.164],[0,0],[2.437,-0.241],[0.96,-0.385]],"v":[[18.761,22.54],[10.669,2.206],[6.547,-10.837],[6.539,-10.88],[10.095,-20.822],[13.377,-24.946],[14.074,-26.286],[-19.37,-19.764],[-11.734,-15.627],[0.046,-2.235],[8.06,23.852],[10.624,26.046],[17.372,24.764]]}},"nm":"Path 1"},{"ty":"fl","fillEnabled":true,"c":{"k":[0.96,0.95,0.9,1]},"o":{"k":100},"nm":"Fill 1"},{"ty":"tr","p":{"k":[44.766,93.955],"ix":2},"a":{"k":[0,0],"ix":1},"s":{"k":[100,100],"ix":3},"r":{"k":0,"ix":6},"o":{"k":100,"ix":7},"sk":{"k":0,"ix":4},"sa":{"k":0,"ix":5},"nm":"Transform"}],"nm":"Group 3"},{"ty":"gr","it":[{"ind":0,"ty":"sh","closed":true,"ks":{"k":{"i":[[0.312,0.751],[0,0],[0.651,6.277],[0.002,0.015],[-2.884,2.784],[-0.615,1.041],[-0.243,0.474],[0,0],[-4.446,-1.093],[-2.674,-8.164],[0,0],[-2.437,0.24],[-0.345,0.044],[0,0],[0,0],[-0.072,0.068],[0,0],[0,0]],"o":[[-0.61,-1.468],[0,0],[-0.002,-0.016],[-0.872,-6.566],[1.614,-1.559],[0.224,-0.424],[0,0],[0,0],[5.511,1.355],[2.675,8.164],[0,0],[0.321,-0.032],[0,0],[0,0],[0.088,-0.056],[0,0],[0,0],[0.32,-0.325]],"v":[[18.91,21.685],[10.818,1.35],[6.695,-11.692],[6.688,-11.735],[10.243,-21.677],[13.525,-25.801],[14.222,-27.141],[-19.221,-20.619],[-11.585,-16.482],[0.195,-3.09],[8.208,22.996],[10.773,25.19],[11.776,25.074],[13.853,27.141],[18.499,23.447],[18.736,23.259],[18.781,23.223],[18.779,23.223]]}},"nm":"Path 1"},{"ty":"fl","fillEnabled":true,"c":{"k":[0.89,0.86,0.81,1]},"o":{"k":100},"nm":"Fill 1"},{"ty":"tr","p":{"k":[49.618,90.81],"ix":2},"a":{"k":[0,0],"ix":1},"s":{"k":[100,100],"ix":3},"r":{"k":0,"ix":6},"o":{"k":100,"ix":7},"sk":{"k":0,"ix":4},"sa":{"k":0,"ix":5},"nm":"Transform"}],"nm":"Group 4"}],"ip":0,"op":450,"st":0,"bm":0,"sr":1},{"ddd":0,"ind":1,"ty":4,"nm":"\rball","ks":{"o":{"k":100},"r":{"k":0},"p":{"k":[{"i":{"x":0.9,"y":1},"o":{"x":0.1,"y":0},"n":"0p9_1_0p1_0","t":0,"s":[379.51,644.771,0],"e":[504.346,338.771,0],"to":[64,-174.66667175293,0],"ti":[-92,60.6666679382324,0]},{"i":{"x":0.9,"y":1},"o":{"x":0.1,"y":0},"n":"0p9_1_0p1_0","t":12.167,"s":[504.346,338.771,0],"e":[304.346,476.771,0],"to":[-93.685432434082,-2.54076671600342,0],"ti":[14.7961158752441,-54.6596870422363,0]},{"i":{"x":0.9,"y":1},"o":{"x":0.1,"y":0},"n":"0p9_1_0p1_0","t":26.333,"s":[304.346,476.771,0],"e":[150.346,494.771,0],"to":[-79.2961196899414,-16.340311050415,0],"ti":[0,0,0]},{"i":{"x":0.9,"y":1},"o":{"x":0.1,"y":0},"n":"0p9_1_0p1_0","t":37,"s":[150.346,494.771,0],"e":[504.346,341.771,0],"to":[0,0,0],"ti":[0,0,0]},{"i":{"x":0.9,"y":1},"o":{"x":0.1,"y":0},"n":"0p9_1_0p1_0","t":48.667,"s":[504.346,341.771,0],"e":[427.346,585.771,0],"to":[0,0,0],"ti":[15.3459930419922,-108.228988647461,0]},{"i":{"x":0.9,"y":1},"o":{"x":0.1,"y":0},"n":"0p9_1_0p1_0","t":60.833,"s":[427.346,585.771,0],"e":[379.51,644.771,0],"to":[-33.3459930419922,11.2289886474609,0],"ti":[-5.00135564804077,13.6495332717896,0]},{"t":71}]},"a":{"k":[11.5,11.499,0]},"s":{"k":[100,100,100]}},"shapes":[{"ty":"gr","it":[{"ind":0,"ty":"sh","closed":true,"ks":{"k":{"i":[[0,-6.213],[6.212,0],[0,6.213],[-6.213,0]],"o":[[0,6.213],[-6.213,0],[0,-6.213],[6.212,0]],"v":[[11.25,0],[0,11.249],[-11.25,0],[0,-11.249]]}},"nm":"Path 1"},{"ty":"fl","fillEnabled":true,"c":{"k":[0.98,0.99,0.34,1]},"o":{"k":100},"nm":"Fill 1"},{"ty":"tr","p":{"k":[11.499,11.499],"ix":2},"a":{"k":[0,0],"ix":1},"s":{"k":[100,100],"ix":3},"r":{"k":0,"ix":6},"o":{"k":100,"ix":7},"sk":{"k":0,"ix":4},"sa":{"k":0,"ix":5},"nm":"Transform"}],"nm":"Group 1"}],"ip":0,"op":450,"st":0,"bm":0,"sr":1},{"ddd":0,"ind":2,"ty":4,"nm":"\rshadow","ks":{"o":{"k":70},"r":{"k":0},"p":{"k":[{"i":{"x":0.833,"y":0.833},"o":{"x":0.167,"y":0.167},"n":"0p833_0p833_0p167_0p167","t":0,"s":[377.346,671.771,0],"e":[501.346,442.771,0],"to":[20.6666660308838,-38.1666679382324,0],"ti":[0,0,0]},{"i":{"x":0.833,"y":0.833},"o":{"x":0.167,"y":0.167},"n":"0p833_0p833_0p167_0p167","t":12.167,"s":[501.346,442.771,0],"e":[303.846,484.771,0],"to":[0,0,0],"ti":[0,0,0]},{"i":{"x":0.833,"y":0.833},"o":{"x":0.167,"y":0.167},"n":"0p833_0p833_0p167_0p167","t":26,"s":[303.846,484.771,0],"e":[146.346,531.771,0],"to":[0,0,0],"ti":[-32.25,7.83333349227905,0]},{"i":{"x":0.833,"y":0.833},"o":{"x":0.167,"y":0.167},"n":"0p833_0p833_0p167_0p167","t":36.5,"s":[146.346,531.771,0],"e":[497.346,437.771,0],"to":[32.25,-7.83333349227905,0],"ti":[0,0,0]},{"i":{"x":0.833,"y":0.833},"o":{"x":0.167,"y":0.167},"n":"0p833_0p833_0p167_0p167","t":48.667,"s":[497.346,437.771,0],"e":[426.346,594.271,0],"to":[0,0,0],"ti":[0,0,0]},{"i":{"x":0.833,"y":0.833},"o":{"x":0.167,"y":0.167},"n":"0p833_0p833_0p167_0p167","t":61,"s":[426.346,594.271,0],"e":[377.346,671.771,0],"to":[0,0,0],"ti":[8.16666698455811,-12.9166669845581,0]},{"t":71}]},"a":{"k":[11.499,5.875,0]},"s":{"k":[100,100,100]}},"shapes":[{"ty":"gr","it":[{"ind":0,"ty":"sh","closed":true,"ks":{"k":{"i":[[0,-3.106],[6.212,0],[0,3.106],[-6.213,0]],"o":[[0,3.106],[-6.213,0],[0,-3.106],[6.212,0]],"v":[[11.25,0],[0,5.625],[-11.25,0],[0,-5.625]]}},"nm":"Path 1"},{"ty":"fl","fillEnabled":true,"c":{"k":[0.59,0.18,0.26,1]},"o":{"k":100},"nm":"Fill 1"},{"ty":"tr","p":{"k":[11.499,5.875],"ix":2},"a":{"k":[0,0],"ix":1},"s":{"k":[100,100],"ix":3},"r":{"k":0,"ix":6},"o":{"k":100,"ix":7},"sk":{"k":0,"ix":4},"sa":{"k":0,"ix":5},"nm":"Transform"}],"nm":"Group 1"}],"ip":0,"op":450,"st":0,"bm":0,"sr":1},{"ddd":1,"ind":3,"ty":0,"nm":"table 1 player","refId":"comp_0","ks":{"o":{"k":100},"rx":{"k":0},"ry":{"k":0},"rz":{"k":0},"or":{"k":[0,0,0]},"p":{"k":[388,385,0]},"a":{"k":[388,385,0]},"s":{"k":[100,100,100]}},"w":776,"h":770,"ip":0,"op":450,"st":0,"bm":0,"sr":1}],"v":"4.4.12","ddd":1,"ip":0,"op":74,"fr":30,"w":776,"h":770}